{
  "title": "손과 마음으로 회복을 돕는 길 — 작업치료사 국가시험 완전 정복",
  "summary": "작업치료사 국가시험(국시)의 시험 과목·합격 기준·연도별 합격률부터 과목별 공부법, 교재 선택, 합격 후 진로까지 한 번에 정리한 가이드다.",
  "tags": ["작업치료사", "국가시험", "재활", "의료", "자격증", "보건의료", "국시"],
  "relatedJobs": [
    {"slug": "작업치료사", "name": "작업치료사"},
    {"slug": "물리치료사", "name": "물리치료사"},
    {"slug": "언어치료사", "name": "언어치료사"},
    {"slug": "언어재활사", "name": "언어재활사"},
    {"slug": "재활의학과전문의사", "name": "재활의학과전문의사"},
    {"slug": "장애인재활상담사", "name": "장애인재활상담사"}
  ],
  "relatedMajors": [
    {"slug": "작업치료학과", "name": "작업치료학과"},
    {"slug": "작업치료과", "name": "작업치료과"},
    {"slug": "재활학과", "name": "재활학과"},
    {"slug": "물리치료학과", "name": "물리치료학과"},
    {"slug": "스포츠재활과", "name": "스포츠재활과"}
  ],
  "thumbnailUrl": "/uploads/jobs/job-HowTo-ot-exam.webp"
}
