{
  "fields": {
    "way": "도시재생코디네이터는 도시재생 현장에서 주민, 지방자치단체, 사업 시행자 사이를 매개하며 사업이 원활히 진행될 수 있도록 조율·지원하는 현장 전문가이다. 진입 경로는 도시계획학·건축학·사회학·행정학 등 관련 전공 학사 이상 학위 취득 후 지방자치단체 도시재생 지원센터 또는 도시재생 관련 공공기관(LH, 지역 도시공사 등)에 취업하는 것이 일반적이다. 국토교통부에서 인정한 교육기관의 '도시재생 코디네이터 양성과정' 이수 후 활동하는 경로도 있으며, 주민 참여 프로그램 기획, 마을 활동가 경험, 사회적경제 관련 경험이 있으면 취업에 유리하다. 이와 함께 도시계획기사 등 관련 자격증 보유나 대학원 도시재생 전공 석사 학위도 경쟁력을 높이는 요소이다.[1]",
    "overviewSalary": {
      "sal": "공공 도시재생 지원센터 소속 코디네이터는 계약직 기준 연 2,800만~3,800만 원 수준으로 시작하며, 경력이 쌓이면 연 4,000만~4,500만 원 수준으로 상승한다. LH·지역 공사 등 대형 공공기관 소속의 경우 정규직 기준 연 3,500만~5,000만 원 수준이다.[1]"
    },
    "overviewProspect": {
      "main": "도시재생 뉴딜 사업, 주거지 재생 사업, 스마트시티 연계 사업 등 관련 정책이 지속 확대됨에 따라 현장 조율 인력으로서의 도시재생코디네이터 수요는 안정적으로 유지될 전망이다. 특히 지역 주민과의 커뮤니케이션 및 갈등 조정 역량이 강조되면서 사회복지·커뮤니티 경험을 갖춘 전문가에 대한 수요가 높아지고 있다.[1]"
    },
    "trivia": "도시재생코디네이터는 단순 행정 지원을 넘어 주민 역량 강화 교육, 로컬 콘텐츠 기획, 지역 창업 지원 등 다양한 역할을 수행하며, 일부 코디네이터들은 현장 활동 경험을 살려 마을기업·사회적기업을 직접 창업하거나 도시재생 분야 강사로 활동하는 등 커리어를 다각화하고 있다.[1]",
    "detailWlb": {
      "wlb": "보통 이상",
      "social": "높음",
      "wlbDetail": "지자체 지원센터 소속의 경우 정해진 근무 시간 내에 일하는 것이 일반적이나, 주민 회의·워크숍·현장 방문 등 저녁이나 주말 외근이 발생할 수 있다. 행정 서류 작업과 현장 활동이 교차하는 업무 구조로, 규칙적인 생활 패턴을 유지하기 다소 어려울 수 있으나 사회적 보람과 현장 밀착성이 높아 직업 만족도는 양호한 편이다.[1]",
      "socialDetail": "노후 지역의 물리적 환경을 개선하는 동시에 주민 공동체를 재건하고 지역 문화를 보전하며, 지역 내 소규모 창업과 경제 활성화를 지원하는 다면적 사회 공헌 역할을 담당한다.[1]"
    },
    "youtubeLinks": [],
    "detailReady": {
      "curriculum": [
        {
          "title": "도시계획학·도시공학과(학사·석사)",
          "text": "도시 문제 분석, 재생 계획 수립, 공간 기획 이론을 배우며 도시재생 현장의 전문적 이해를 갖출 수 있다.",
          "link": null
        },
        {
          "title": "사회학·행정학·지역개발학과",
          "text": "주민 참여, 지역 커뮤니티 운영, 갈등 관리 이론을 다루며 코디네이터로서의 현장 소통 역량을 키울 수 있다.",
          "link": null
        },
        {
          "title": "국토교통부 인정 도시재생 코디네이터 양성과정",
          "text": "도시재생 사업 이해, 현장 운영, 주민 참여 촉진, 갈등 조정 등 코디네이터 핵심 역량을 실무 중심으로 교육한다.",
          "link": null
        },
        {
          "title": "건축학·환경설계학과",
          "text": "노후 건물 리모델링, 공공 공간 조성, 마을 환경 개선 설계 역량을 배양하며 현장 기반 재생 프로젝트에 연계된다.",
          "link": null
        },
        {
          "title": "사회적기업·마을기업 실무 과정",
          "text": "지역 자원 발굴, 커뮤니티 비즈니스, 마을기업 운영 등 도시재생 현장의 경제 활성화 역량을 키우는 과정이다.[1]",
          "link": null
        }
      ],
      "recruit": [
        {
          "title": "지자체 도시재생 지원센터 코디네이터 채용",
          "text": "각 시·군·구 도시재생 지원센터에서 계약직·공무직 코디네이터를 채용하며, 워크넷 또는 지자체 채용 페이지에서 확인 가능하다.",
          "link": "https://www.work.go.kr/"
        },
        {
          "title": "LH·지역 도시공사 도시재생 직무 채용",
          "text": "한국토지주택공사(LH)와 지역 도시공사에서 도시재생 코디네이터·운영 지원 직무를 공채 또는 경력직으로 채용한다.",
          "link": "https://www.lh.or.kr/"
        },
        {
          "title": "민간 도시재생 전문기업·사회적기업 채용",
          "text": "사람인·잡코리아에서 '도시재생 코디네이터', '마을 활동가', '지역 커뮤니티 기획' 키워드로 검색하면 민간 채용 정보를 찾을 수 있다.[1]",
          "link": "https://www.saramin.co.kr"
        }
      ],
      "training": [
        {
          "title": "HRD-Net 도시재생·지역개발 관련 직업훈련과정",
          "text": "도시재생 코디네이터, 마을 활동가, 지역 커뮤니티 운영 관련 훈련과정을 조회할 수 있다.",
          "link": "https://www.hrd.go.kr/"
        },
        {
          "title": "국토교통부 도시재생 종합정보체계 전문 교육",
          "text": "도시재생 현장 운영 실무, 주민 참여 촉진, 사업 관리 관련 온·오프라인 전문 교육과정을 제공한다.[1]",
          "link": "https://www.city.go.kr/"
        }
      ]
    },
    "heroTags": [
      "도시재생",
      "코디네이터",
      "주민참여",
      "커뮤니티기획",
      "지역활성화",
      "현장전문가"
    ],
    "sidebarJobs": [
      "도시재생기획운영가",
      "도시계획가",
      "사회복지사",
      "지역개발전문가",
      "도시마케터"
    ],
    "sidebarCerts": [
      {
        "name": "도시계획기사",
        "url": "https://www.q-net.or.kr/crf005.do?id=crf00503&gSite=Q&jmCd=1811"
      },
      {
        "name": "주택관리사",
        "url": "https://www.q-net.or.kr/crf005.do?id=crf00503&gSite=Q&jmCd=6070"
      },
      {
        "name": "사회조사분석사2급",
        "url": "https://www.q-net.or.kr/crf005.do?id=crf00503&gSite=Q&jmCd=1160"
      }
    ]
  },
  "sources": {
    "way": [
      {
        "id": 1,
        "text": "[1] 커리어넷 직업정보",
        "url": "https://www.career.go.kr/"
      }
    ],
    "overviewSalary.sal": [
      {
        "id": 1,
        "text": "[1] 워크넷 임금정보",
        "url": "https://www.work.go.kr/"
      }
    ],
    "overviewProspect.main": [
      {
        "id": 1,
        "text": "[1] 국토교통부 도시재생 뉴딜 정책자료",
        "url": "https://www.molit.go.kr/"
      }
    ],
    "trivia": [
      {
        "id": 1,
        "text": "[1] 도시재생 종합정보체계",
        "url": "https://www.city.go.kr/"
      }
    ],
    "detailWlb.wlbDetail": [
      {
        "id": 1,
        "text": "[1] 커리어넷 직업정보",
        "url": "https://www.career.go.kr/"
      }
    ],
    "detailWlb.socialDetail": [
      {
        "id": 1,
        "text": "[1] 커리어넷 직업정보",
        "url": "https://www.career.go.kr/"
      }
    ],
    "detailReady.curriculum": [
      {
        "id": 1,
        "text": "[1] 커리어넷 직업정보",
        "url": "https://www.career.go.kr/"
      }
    ],
    "detailReady.recruit": [
      {
        "id": 1,
        "text": "[1] 워크넷 채용정보",
        "url": "https://www.work.go.kr/"
      }
    ],
    "detailReady.training": [
      {
        "id": 1,
        "text": "[1] HRD-Net 직업훈련포털",
        "url": "https://www.hrd.go.kr/"
      }
    ]
  },
  "changeSummary": "도시재생코디네이터 way·sal·prospect·trivia·wlb·detailReady·heroTags·sidebarJobs·sidebarCerts 신규 보완"
}