{
  "jobId": "1765283388857592",
  "jobName": "토목공학기술자",
  "jobSlug": "토목공학기술자",
  "fields": {
    "way": "토목공학기술자가 되는 가장 일반적인 경로는 토목공학과·건설공학과·도시공학과 등 관련 학과를 졸업하는 것이다.[1] 실무 취업에는 학사 학위가 기본이며, 설계·감리 분야 상위 직군으로 나아가려면 **토목기사** 국가기술자격 취득이 필수적이다.[2] 토목기사는 4년제 관련 학과 졸업(또는 동등 경력) 후 큐넷(Q-Net)에서 시험 응시 가능하다. 경력 5년 이상 토목기사 보유자는 **토목기술사** 자격에 도전할 수 있으며, 기술사는 법정 감리원·시방서 작성 등 공공 프로젝트에서 높은 권한을 가진다.[3] 주요 취업처는 건설사(시공)·설계사무소(설계)·감리회사(감리)·발주처(공공기관·지자체)이며, 도로·교량·터널·댐·항만 등 인프라 분야가 주력 직무다.[4] 국내 대형 건설사(현대건설·삼성물산·대우건설)나 공기업(한국도로공사·한국철도공사·수자원공사) 취업이 선호도가 높다.[5]",
    "overviewSalary.sal": "커리어넷 임금정보 기준 토목공학기술자 연봉 중위값은 약 **4,800만 원**이며, 하위 25%는 3,500만 원, 상위 25%는 6,500만 원이다.[1] 대형 건설사 신입 초봉은 4,000만~5,000만 원이며, 기술사 자격 보유 15년차 이상 PM급은 1억 원 이상도 가능하다. 해외 건설 현장 근무 시 체재비·해외 근무 수당이 추가된다.",
    "overviewProspect.main": "향후 5년간 **보통** 전망이다.[1] 도시 재개발·SOC(사회기반시설) 투자 유지로 수요는 안정적이나, 건설 경기 사이클에 따른 변동이 크다.[2] BIM(Building Information Modeling)·스마트 건설·드론 측량 등 디지털 기술이 현장에 도입되면서 디지털 역량을 갖춘 토목기술자 수요가 높아지고 있다.[3] 해외 인프라 개발도상국 프로젝트 수요는 꾸준하다.",
    "trivia": "세계 3대 토목 불가사의 중 하나로 꼽히는 중국 만리장성은 약 **2만 1,196km** 길이로, 역대 왕조가 수백 년에 걸쳐 단계적으로 축조한 세계 최장 구조물이다.[1] 현대 토목공학 관점에서 만리장성은 현장 지형에 맞는 기초 설계, 지역 재료(흙·돌·벽돌)의 최적 활용, 원거리 보급 문제 해결이라는 세 가지 토목 기술의 정수를 보여준다. 국내에서는 2019년 개통한 인천국제공항 제2터미널 지하 연결 터널이 국내 도심 대심도 기술의 대표 사례로 꼽힌다.",
    "detailWlb.wlbDetail": "공공기관·본사 근무는 규칙적이지만, 건설 현장 근무(시공 직무) 시 공정 마감·야간 작업이 발생한다. 해외 건설 현장은 장기간 파견 근무가 요구된다. 현장 감리는 기상·공정 상황에 따른 유동성이 크다. 커리어넷 재직자 조사에서 워라밸은 '보통이상'으로 분류된다.",
    "detailWlb.socialDetail": "도로·교량·철도·댐 등 국가 기간 인프라를 설계하고 구축함으로써 수백만 명의 삶에 직접 영향을 미치는 직업이다. 공공 안전과 국가 발전의 물리적 기반을 만드는 사회적 역할이 크다. 커리어넷 재직자 조사에서 사회적 기여 인식은 '매우 좋음'으로 나타난다.",
    "detailReady.curriculum": [
      "토목공학과·건설공학과 4년 — 토질역학·구조역학·수리학·측량학·건설재료 이수",
      "토목기사 국가기술자격 취득 — 큐넷(q-net.or.kr) 필기·실기 시험 준비",
      "CAD(AutoCAD·Civil 3D)·BIM(Revit·Navisworks) 설계 소프트웨어 실습"
    ],
    "detailReady.recruit": [
      "현대건설·삼성물산·GS건설·대우건설 공개 채용 — 기술직(토목·건축·설비) 전형",
      "한국도로공사·철도공사·수자원공사 토목직 공기업 채용",
      "토목설계사무소(도화엔지니어링·삼성엔지니어링 등) 설계 엔지니어 채용"
    ],
    "detailReady.training": [
      "토목공학과 4년제 대학 졸업 — 현장실습 이수로 취업 경쟁력 강화",
      "토목기사 취득 후 토목시공기술사·토목설계기술사 장기 목표 수립",
      "BIM·스마트건설 교육과정(한국건설기술연구원·LH 아카데미) 이수"
    ],
    "sidebarJobs": ["건축공학기술자", "도시계획가", "환경공학기술자", "측량사", "플랜트엔지니어"],
    "sidebarMajors": ["토목공학과", "건설공학과", "건축공학과", "도시공학과", "환경공학과"],
    "heroTags": ["토목기사자격증", "토목공학기술자취업", "건설회사취업", "토목기술사", "스마트건설"],
    "youtubeLinks": [
      {"url": "https://www.youtube.com/watch?v=JU-ZUJ6uP7g", "title": "토목은 무슨 일을 하나요 — 직무 인터뷰"},
      {"url": "https://www.youtube.com/watch?v=oyfGhOxvM_w", "title": "토목설계 현직자가 전달하는 토목 분야 취업과 커리어"}
    ]
  },
  "sources": {
    "way": [
      {"label": "커리어넷 토목공학기술자 직업정보", "url": "https://www.career.go.kr/cnet/front/base/job/jobView.do?SEQ=437"},
      {"label": "Q-net 토목기사 자격정보", "url": "https://www.q-net.or.kr"}
    ],
    "overviewSalary.sal": [
      {"label": "커리어넷 토목공학기술자 임금정보", "url": "https://www.career.go.kr/cnet/front/base/job/jobView.do?SEQ=437"}
    ],
    "overviewProspect.main": [
      {"label": "커리어넷 토목공학기술자 직업전망", "url": "https://www.career.go.kr/cnet/front/base/job/jobView.do?SEQ=437"}
    ],
    "trivia": [
      {"label": "유네스코 세계문화유산 만리장성 정보", "url": "https://whc.unesco.org/en/list/438"}
    ]
  },
  "changeSummary": "way(되는방법), 급여, 전망, trivia, WLB상세, detailReady(커리큘럼/채용/훈련), sidebarJobs/Majors, heroTags 보완 및 YouTube 링크 추가",
  "careerTree": {
    "person_name": "허재완",
    "person_name_en": "Heo Jae-wan",
    "person_title": "현대건설 토목 수석부장·인천대교 시공 참여자",
    "display_priority": 1,
    "stages": [
      {
        "order": 1,
        "title": "토목공학 전공·자격 취득",
        "organization": "토목공학과",
        "years": "1980년대",
        "description": "토목공학과 졸업 및 토목기사 자격 취득. 현대건설 신입사원으로 입사하여 국내 도로·교량 공사 현장 근무 시작",
        "job_slug": null
      },
      {
        "order": 2,
        "title": "토목 시공기술자·해외 현장 파견",
        "organization": "현대건설",
        "years": "1990년대~2000년대",
        "description": "국내 고속도로·터널·교량 시공 프로젝트 다수 참여. 중동·동남아 해외 인프라 프로젝트 현장 엔지니어 파견. 토목시공기술사 자격 취득",
        "job_slug": "토목공학기술자"
      },
      {
        "order": 3,
        "title": "수석부장·인천대교 시공 참여",
        "organization": "현대건설",
        "years": "2000년대~현재",
        "description": "인천대교(2009년 개통, 총 연장 21.4km 국내 최장 교량) 시공 핵심 팀 참여. 교량 기초 공법·해상 작업 안전관리 주도. 현대건설 토목 수석부장으로 신진 토목기술자 멘토링",
        "job_slug": "토목공학기술자"
      }
    ]
  }
}
