{
  "jobId": "1765284498834583",
  "jobName": "보험설계사",
  "jobSlug": "보험설계사",
  "fields": {
    "way": "보험설계사가 되려면 금융감독원에 등록된 **보험모집인** 자격을 취득해야 한다. 보험회사나 보험대리점(GA)에 소속되어 2~4주 교육 이수 후 자격 시험에 합격하면 즉시 업무를 시작할 수 있다.[1] 주요 경로는 삼성생명·한화생명·교보생명·현대해상 등 생손보사의 직속 설계사로 입사하거나, 법인보험대리점(GA)에 소속하는 방식이다.[2] 특별한 학력 기준이 없어 진입 장벽이 낮다. 설계사 등록 후 생명보험·손해보험·제3보험(건강보험) 등 각 분야 판매 자격을 별도 취득해 다양한 상품을 판매할 수 있다.",
    "overviewSalary.sal": "커리어넷 임금정보 기준 보험설계사 연봉 중위값은 약 **3,500만 원**이며, 하위 25%는 1,500만 원, 상위 25%는 6,000만 원이다.[1] 수수료 기반 소득 구조로 성과에 따라 수입 편차가 매우 크다. 상위 1% 설계사는 연 수억 원의 수입을 올리는 반면, 신입 설계사의 50% 이상이 3년 내 이탈한다. 고객 포트폴리오 구축 후 안정적 수입이 가능한 구조다.",
    "overviewProspect.main": "향후 5년간 **감소** 전망이다.[1] 보험 다이렉트 판매(온라인·앱) 확대와 AI 보험 추천 플랫폼 성장으로 단순 상품 판매 중심 설계사 수요가 감소하고 있다. 반면 복잡한 자산 관리·세금·은퇴 설계를 결합한 종합 재무 설계사로의 전문화는 여전히 수요가 있다.",
    "trivia": "한국의 등록 보험설계사 수는 2024년 기준 약 **40만 명**이지만, 연간 이직률이 30% 이상으로 실질 활동 설계사는 20만~25만 명 수준이다.[1] 보험설계사는 전업주부·중장년층 재취업자가 많은 직업으로, 유연한 근무 시간이 특징이다. 금융소비자보호법(2021) 시행 이후 불완전판매 규제가 강화되어 전문 지식 기반 설계 역량이 더욱 중요해졌다.",
    "detailWlb.wlbDetail": "근무 시간은 자율적이지만 실적 달성 압박과 고객 관리(야간·주말 미팅)로 실질적 자유는 제한적이다. 신규 고객 발굴(영업)의 지속적 필요성으로 심리적 부담이 있다. 안정적 고객 기반 구축 후에는 비교적 자유로운 시간 관리가 가능하다. 커리어넷 재직자 조사에서 워라밸은 '보통이상'으로 분류된다.",
    "detailWlb.socialDetail": "고객의 재정 위험을 대비하고 예상치 못한 사고·질병에서 경제적 안전망을 제공하는 사회적 역할이다. 복잡한 보험 상품을 이해하기 쉽게 안내해 금융 소외층의 보험 접근성을 높이는 데 기여한다. 커리어넷 재직자 조사에서 사회적 기여 인식은 '보통이상'으로 나타난다.",
    "detailReady.curriculum": [
      "보험설계사 등록 교육 수료 — 소속 보험사·GA의 2~4주 집합 교육 및 금융감독원 모집인 등록",
      "생명보험·손해보험·제3보험 자격증 취득 — 생명보험협회(klia.or.kr)·손해보험협회(knia.or.kr) 시험 응시",
      "CFP(국제공인재무설계사) 또는 AFPK 자격 취득 — 종합 재무 설계사로 전문성 강화"
    ],
    "detailReady.recruit": [
      "삼성생명·한화생명·교보생명 등 대형 생보사 직속 설계사 채용",
      "법인보험대리점(GA: 피플라이프·GA코리아 등) 보험설계사 등록",
      "은행·증권사 보험 판매 채널(방카슈랑스) 소속 보험설계사 등록"
    ],
    "detailReady.training": [
      "AFPK(재무설계사)·CFP(국제공인재무설계사) 취득 — 보험 외 세금·연금·부동산 종합 설계 역량 강화",
      "변액보험 자격 취득 — 투자형 보험 상품 판매 자격, 보험 상품 라인업 확장",
      "디지털 보험 플랫폼(보험다모아·카카오보험) 활용 교육 — 비대면 설계 역량 강화"
    ],
    "sidebarJobs": ["재무설계사", "투자분석가", "은행원", "부동산중개사", "세무사"],
    "sidebarMajors": ["경영학과", "경제학과", "금융보험학과", "통계학과", "사회복지학과"],
    "heroTags": ["보험모집인자격증", "종합재무설계사", "CFP재무설계전문가", "생명보험전문가", "GA소속보험설계사"],
    "youtubeLinks": [
      {"url": "https://www.youtube.com/watch?v=ZVUgRt6UDu8", "title": "현실적인 보험설계사 인터뷰 — 수익구조·연봉"},
      {"url": "https://www.youtube.com/watch?v=BEVXWdmbVTE", "title": "보험설계사 직업 인터뷰 2편"}
    ]
  },
  "sources": {
    "way": [
      {"label": "금융감독원 보험설계사 등록 안내", "url": "https://www.fss.or.kr"},
      {"label": "커리어넷 보험설계사 직업정보", "url": "https://www.career.go.kr/cnet/app/base/job/jobView.m?SEQ=388"}
    ],
    "overviewSalary.sal": [
      {"label": "커리어넷 보험설계사 임금정보", "url": "https://www.career.go.kr/cnet/app/base/job/jobView.m?SEQ=388"}
    ],
    "overviewProspect.main": [
      {"label": "커리어넷 보험설계사 직업전망", "url": "https://www.career.go.kr/cnet/app/base/job/jobView.m?SEQ=388"}
    ],
    "trivia": [
      {"label": "생명보험협회 설계사 현황 통계 2024", "url": "https://www.klia.or.kr"}
    ]
  },
  "changeSummary": "way(되는방법), 급여, 전망, trivia, WLB상세, detailReady(커리큘럼/채용/훈련), sidebarJobs/Majors, heroTags 보완 및 YouTube 링크 추가",
  "careerTree": {
    "person_name": "정문국",
    "person_name_en": "Jung Moon-kuk",
    "person_title": "오렌지라이프(구 ING생명) 전 대표이사·보험전문가",
    "display_priority": 1,
    "stages": [
      {
        "order": 1,
        "title": "보험설계사 입직",
        "organization": "생명보험회사",
        "years": "1990년대",
        "description": "생명보험회사 보험설계사로 업무 시작. 고객 발굴·재무 설계·보험 상품 판매 실무 역량 구축",
        "job_slug": null
      },
      {
        "order": 2,
        "title": "보험설계사·관리자",
        "organization": "ING생명(현 오렌지라이프)",
        "years": "2000년대~2010년대",
        "description": "보험 영업 부문 관리자 역임. 전속 설계사 조직 관리·교육·성과 관리. 팀장→지점장 승진",
        "job_slug": "보험설계사"
      },
      {
        "order": 3,
        "title": "오렌지라이프 대표이사",
        "organization": "오렌지라이프(구 ING생명)",
        "years": "2010년대",
        "description": "대표이사로 오렌지라이프 디지털 전환·수수료 구조 개선·GA 채널 확장 주도. 현장 설계사 출신 보험사 CEO로 주목",
        "job_slug": "보험설계사"
      }
    ]
  }
}
